cree_sro_syllabics.py
crk_orthography.py
crk_orthography-0.20181108.1.dist-info/LICENSE
crk_orthography-0.20181108.1.dist-info/METADATA
crk_orthography-0.20181108.1.dist-info/WHEEL
crk_orthography-0.20181108.1.dist-info/top_level.txt
crk_orthography-0.20181108.1.dist-info/RECORD
