Metadata-Version: 2.1
Name: crk-orthography
Version: 0.20181108.1
Summary: Convert between Plains Cree SRO and syllabics
Home-page: https://github.com/eddieantonio/crk_orthography
Author: Eddie Antonio Santos
Author-email: easantos@ualberta.ca
License: AGPLv3
Platform: UNKNOWN
Classifier: License :: OSI Approved :: GNU Affero General Public License v3
Classifier: Programming Language :: Python
Classifier: Programming Language :: Python :: 3
Classifier: Programming Language :: Python :: 3.4
Classifier: Programming Language :: Python :: 3.5
Classifier: Programming Language :: Python :: 3.6
Classifier: Programming Language :: Python :: 3.7
Classifier: Programming Language :: Python :: Implementation :: CPython
Classifier: Programming Language :: Python :: Implementation :: PyPy
Requires-Python: >=3.4.0
